propelauth_byo/__init__.py
propelauth_byo/api_key_client.py
propelauth_byo/device_client.py
propelauth_byo/impersonation_client.py
propelauth_byo/passkey_client.py
propelauth_byo/propel_auth_client.py
propelauth_byo/result.py
propelauth_byo/scim_client.py
propelauth_byo/scim_management_client.py
propelauth_byo/session_client.py
propelauth_byo/sso_client.py
propelauth_byo/sso_management_client.py
propelauth_byo/types.py
propelauth_byo/generated/__init__.py
propelauth_byo/generated/api_key_error.py
propelauth_byo/generated/api_key_full_metadata_response.py
propelauth_byo/generated/api_key_status.py
propelauth_byo/generated/command.py
propelauth_byo/generated/commit_scim_user_change_command.py
propelauth_byo/generated/commit_scim_user_change_error.py
propelauth_byo/generated/complete_oidc_login_command.py
propelauth_byo/generated/complete_oidc_login_error.py
propelauth_byo/generated/complete_oidc_login_response.py
propelauth_byo/generated/complete_scim_user_response.py
propelauth_byo/generated/completed_scim_request_response.py
propelauth_byo/generated/create_api_key_command.py
propelauth_byo/generated/create_api_key_error.py
propelauth_byo/generated/create_api_key_response.py
propelauth_byo/generated/create_device_challenge_command.py
propelauth_byo/generated/create_device_challenge_error.py
propelauth_byo/generated/create_device_challenge_response.py
propelauth_byo/generated/create_impersonation_session_command.py
propelauth_byo/generated/create_impersonation_session_error.py
propelauth_byo/generated/create_impersonation_session_response.py
propelauth_byo/generated/create_oidc_client_command.py
propelauth_byo/generated/create_oidc_client_error.py
propelauth_byo/generated/create_oidc_client_response.py
propelauth_byo/generated/create_scim_connection_command.py
propelauth_byo/generated/create_scim_connection_error.py
propelauth_byo/generated/create_scim_connection_response.py
propelauth_byo/generated/create_session_command.py
propelauth_byo-1.0.6.dist-info/METADATA
propelauth_byo-1.0.6.dist-info/WHEEL
propelauth_byo-1.0.6.dist-info/top_level.txt
propelauth_byo-1.0.6.dist-info/RECORD
